nex/__init__.py
nex/nex.py
nex/nexLink.py
nex/nexfile.py
nex-1.0.6.dist-info/LICENSE
nex-1.0.6.dist-info/METADATA
nex-1.0.6.dist-info/WHEEL
nex-1.0.6.dist-info/top_level.txt
nex-1.0.6.dist-info/RECORD
