Metadata-Version: 2.1
Name: nex
Version: 1.0.6
Summary: Run NeuroExplorer Python scripts and read and write .nex and .nex5 files in any Python development environment (VS Code, Spyder, etc.).
Author-email: Alex Kirillov <alex@neuroexplorer.com>
Project-URL: homepage, https://github.com/NeuroExplorer/nex-Python-package
Project-URL: documentation, https://www.neuroexplorer.com/docs/reference/scripting/index.html
Project-URL: repository, https://github.com/NeuroExplorer/nex-Python-package
Keywords: NeuroExplorer,nex,nex5,VS Code
Classifier: Programming Language :: Python :: 3
Classifier: License :: OSI Approved :: MIT License
Classifier: Operating System :: OS Independent
Requires-Python: >=3.7
License-File: LICENSE
Requires-Dist: numpy
